[
    {
        "title": "Eiffel Tower of Paris, France",
        "notes": "Composite picturesque image of sunset at the Eiffel tower in spring in Paris, France",
        "date": "October 20, 2020",
        "credit": "Ronak Jethwa",
        "src": "01.jpeg",
        "alt": "Sunset at Eiffel Tower in Paris, France",
        "imgDir": "/images/"
    },
    {
        "title": "Public Market of Seattle, Washington",
        "notes": "Strolling around the famous pike place market on a fine summer evening",
        "date": "October 20, 2020",
        "credit": "Photo by Josh Hild",
        "src": "02.jpeg",
        "alt": "Skybridge over highway covered in water",
        "imgDir": "/images/"
    },
    {
        "title": "Brown painted wall on dim light",
        "notes": "Highway covered in water",
        "date": "October 18, 2020",
        "credit": "Photo by Lukas Hartmann",
        "src": "03.jpeg",
        "alt": "Brown painted wall with two benches and dim light above",
        "imgDir": "/images/"
    },
    {
        "title": "Red light streaks across a street intersection at night",
        "notes": "Highway covered in water",
        "date": "October 16, 2020",
        "credit": "Photo by Jan Kopriva",
        "src": "04.jpeg",
        "alt": "Red light streaks across a street intersection at night",
        "imgDir": "/images/"
    },
    {
        "title": "Abstract architecture black and white boardwalk",
        "notes": "Highway covered in water",
        "date": "October 14, 2020",
        "credit": "Photo by Pixabay",
        "src": "05.jpeg",
        "alt": "Abstract architecture black and white boardwalk with glass like floor",
        "imgDir": "/images/"
    },
    {
        "title": "Person holding glass mason jar with night sky background",
        "notes": "Highway covered in water",
        "date": "October 12, 2020",
        "credit": "Photo by Rakicevic Nenad",
        "src": "06.jpeg",
        "alt": "Person holding glass mason jar with night sky background",
        "imgDir": "/images/"
    },
    {
        "title": "Radio City Music Hall During Night Time",
        "notes": "Highway covered in water",
        "date": "October 11, 2020",
        "credit": "Photo by Bao Dang",
        "src": "07.jpeg",
        "alt": "Music hall with bright lights during night time",
        "imgDir": "/images/"
    },
    {
        "title": "City Building Office Architecture",
        "notes": "Highway covered in water",
        "date": "October 10, 2020",
        "credit": "Photo by Jayson Marquez",
        "src": "08.jpeg",
        "alt": "Tall highrise office building with winding architecture",
        "imgDir": "/images/"
    },
    {
        "title": "Buildings during nighttime",
        "notes": "Highway covered in water",
        "date": "October 9, 2020",
        "credit": "Photo by Aleksandar Pasaric",
        "src": "09.jpeg",
        "alt": "Buildings during nighttime with orange lighting and water below",
        "imgDir": "/images/"
    },
    {
        "title": "Water Droplet Digital Wallpaper",
        "notes": "Highway covered in water",
        "date": "October 11, 2020",
        "credit": "Photo by Sourav Mishra",
        "src": "10.png",
        "alt": "Rain drop bursting water particles upwards into the air",
        "imgDir": "/images/"
    },
    {
        "title": "Man walking on the empty street",
        "date": "October 15, 2020",
        "credit": "Photo by Marco Trinidad",
        "src": "11.jpeg",
        "alt": "An empty road during daytime with fog in the background",
        "imgDir": "/images/"
    },
    {
        "title": "Gasoline station during nighttime",
        "notes": "Highway covered in water",
        "date": "October 23, 2020",
        "credit": "Photo by Artem Saranin",
        "src": "12.jpeg",
        "alt": "Gasoline station during nighttime with glowing red roof lights",
        "imgDir": "/images/"
    }
]